dwspark/__init__.py
dwspark/config.py
dwspark/models/MultiLang.py
dwspark/models/__init__.py
dwspark/models/audio_2_text.py
dwspark/models/character_simulator.py
dwspark/models/knowledge_base.py
dwspark/models/llm_embedding.py
dwspark/models/multi_lang.py
dwspark/models/ppt_generator.py
dwspark/models/pricture_understanding.py
dwspark/models/resume_generator.py
dwspark/models/test.py
dwspark/models/text_2_audio.py
dwspark/models/text_2_picture.py
dwspark/models/voice_synthesis.py
dwspark/utils/__init__.py
dwspark/utils/img_utils.py
dwspark-2025.0.1.dist-info/METADATA
dwspark-2025.0.1.dist-info/WHEEL
dwspark-2025.0.1.dist-info/top_level.txt
dwspark-2025.0.1.dist-info/RECORD
