Metadata-Version: 2.1
Name: dwspark
Version: 2025.0.1
Summary: DataWhale用于星火杯2025的适配sdk
Author: datawhale
Author-email: datawhale@example.com
Requires-Python: >=3.8
Requires-Dist: spark-ai-python
Requires-Dist: loguru
Requires-Dist: cffi
Requires-Dist: gevent
Requires-Dist: greenlet
Requires-Dist: pycparser
Requires-Dist: six
Requires-Dist: websockets
Requires-Dist: websocket-client
Requires-Dist: chardet
Requires-Dist: requests-toolbelt
Requires-Dist: numpy
